pheonixia/ModelingHannibal.py
pheonixia/__init__.py
pheonixia-0.0.1.dist-info/LICENSE
pheonixia-0.0.1.dist-info/METADATA
pheonixia-0.0.1.dist-info/WHEEL
pheonixia-0.0.1.dist-info/top_level.txt
pheonixia-0.0.1.dist-info/RECORD
