Metadata-Version: 2.1
Name: pheonixia
Version: 0.0.1
Summary: a repository for Phoenix-IA models
Home-page: https://github.com/not-lain/phoenixia
License: Apache 2.0 License
Classifier: Topic :: Utilities
Classifier: Programming Language :: Python :: 3.9
License-File: LICENSE
Requires-Dist: setuptools >=42
Requires-Dist: wheel >=0.37
Requires-Dist: torch >=2.2.1
Requires-Dist: huggingface-hub >=0.22
